{"cameraMode":{"drawMode":0,"name":"Shaded","section":"Shading Mode"},"sceneLighting":false,"audioPlay":false,"sceneViewState":{"showFog":true,"showMaterialUpdate":true,"showSkybox":false,"showFlares":true,"showImageEffects":true,"showParticleSystems":true,"showVisualEffectGraphs":true,"m_FxEnabled":false},"in2DMode":false,"pivot":{"x":0.0,"y":46.05547332763672,"z":0.0},"rotation":{"x":-0.157566100358963,"y":0.04531783238053322,"z":-0.007235162891447544,"w":-0.9864243865013123},"size":207.82098388671876,"orthographic":true}